demo_lijunshi_x/main.py
demo_lijunshi_x-0.1.2.dist-info/METADATA
demo_lijunshi_x-0.1.2.dist-info/WHEEL
demo_lijunshi_x-0.1.2.dist-info/entry_points.txt
demo_lijunshi_x-0.1.2.dist-info/top_level.txt
demo_lijunshi_x-0.1.2.dist-info/RECORD
