Metadata-Version: 2.4
Name: demo-lijunshi-x
Version: 0.1.2
Summary: Add your description here
Requires-Python: >=3.10
Requires-Dist: elasticsearch>=9.0.0
Requires-Dist: mcp[cli]>=1.6.0
Requires-Dist: python-dotenv>=1.1.0
